cfhl_auth/__init__.py
cfhl_auth/apps.py
cfhl_auth/urls.py
cfhl_auth/lib/__init__.py
cfhl_auth/lib/managers/__init__.py
cfhl_auth/lib/serializers/__init__.py
cfhl_auth/lib/services/__init__.py
cfhl_auth/lib/services/cfhl_auth.py
cfhl_auth/locale/es/LC_MESSAGES/django.mo
cfhl_auth/locale/es/LC_MESSAGES/django.po
cfhl_auth/templates/code_mail.html
cfhl_auth/templates/code_mail.txt
cfhl_auth-1.0.0a2.dist-info/LICENSE
cfhl_auth-1.0.0a2.dist-info/METADATA
cfhl_auth-1.0.0a2.dist-info/WHEEL
cfhl_auth-1.0.0a2.dist-info/top_level.txt
cfhl_auth-1.0.0a2.dist-info/RECORD
