Metadata-Version: 2.1
Name: cfhl-auth
Version: 1.0.0a2
Summary: Cadefihuila Authorization System
Author-email: Mario Cerón <mario.ceron@cqinversiones.co>
License: GNU GENERAL PUBLIC LICENSE
Keywords: django,cadefihuila
Classifier: License :: Other/Proprietary License
Classifier: Programming Language :: Python :: 3.9
Classifier: Development Status :: 3 - Alpha
Classifier: Framework :: Django
Classifier: Framework :: Django :: 4.1
Classifier: Environment :: Web Environment
Classifier: Operating System :: OS Independent
Classifier: Topic :: Internet :: WWW/HTTP
Requires-Python: >=3.9
License-File: LICENSE
Requires-Dist: Django (==4.1)
Requires-Dist: djangorestframework
Requires-Dist: cfhl-oasis4
